epyk_materials/__init__.py
epyk_materials/core/JsMdcComponents.py
epyk_materials/core/MdcHtml.py
epyk_materials/core/Page.py
epyk_materials/core/__init__.py
epyk_materials/interfaces/Comp.py
epyk_materials/interfaces/CompButtons.py
epyk_materials/interfaces/CompIcons.py
epyk_materials/interfaces/CompInputs.py
epyk_materials/interfaces/CompLists.py
epyk_materials/interfaces/CompMenus.py
epyk_materials/interfaces/CompNavigation.py
epyk_materials/interfaces/CompSelects.py
epyk_materials/interfaces/CompSliders.py
epyk_materials/interfaces/CompTexts.py
epyk_materials/interfaces/__init__.py
epyk_materials-1.0.1.dist-info/LICENSE
epyk_materials-1.0.1.dist-info/METADATA
epyk_materials-1.0.1.dist-info/WHEEL
epyk_materials-1.0.1.dist-info/top_level.txt
epyk_materials-1.0.1.dist-info/RECORD
